qarsmac/__init__.py
qarsmac/calculator.py
qarsmac/model.py
qarsmac/requestor.py
qarsmac/timescaledb.py
qarsmac/validator.py
qarsmac-0.0.3.dist-info/licenses/LICENSE
qarsmac-0.0.3.dist-info/METADATA
qarsmac-0.0.3.dist-info/WHEEL
qarsmac-0.0.3.dist-info/top_level.txt
qarsmac-0.0.3.dist-info/RECORD
