Metadata-Version: 2.4
Name: qarsmac
Version: 0.0.3
Summary: Cliente Python da API de Qualidade do Ar da SMAC.
Author-email: Gustavo Muniz do Carmo <gustavo@esign.com.br>
Maintainer-email: Gustavo Muniz do Carmo <gustavo@esign.com.br>
License-Expression: MIT
Project-URL: Repository, https://github.com/esign-consulting/qualidade-ar-smac/tree/main/apiclient
Project-URL: Issues, https://github.com/esign-consulting/qualidade-ar-smac/issues
Keywords: air-quality,api-client
Classifier: Programming Language :: Python :: 3
Classifier: Operating System :: OS Independent
Classifier: Intended Audience :: Developers
Requires-Python: >=3.9
License-File: LICENSE
Requires-Dist: requests
Provides-Extra: timescaledb
Requires-Dist: psycopg2-binary; extra == "timescaledb"
Dynamic: license-file
